taskkill/README.MD
taskkill/__init__.py
taskkill/requirements.txt
taskkill/thirdparty.json
taskkill-0.10.dist-info/LICENSE.rst
taskkill-0.10.dist-info/METADATA
taskkill-0.10.dist-info/WHEEL
taskkill-0.10.dist-info/top_level.txt
taskkill-0.10.dist-info/RECORD
