Metadata-Version: 2.1
Name: taskkill
Version: 0.10
Summary: terminating processes on Windows using the taskkill command
Home-page: https://github.com/hansalemaos/taskkill
Author: Johannes Fischer
Author-email: aulasparticularesdealemaosp@gmail.com
License: MIT
Keywords: taskkill
Classifier: Development Status :: 4 - Beta
Classifier: Programming Language :: Python :: 3 :: Only
Classifier: Programming Language :: Python :: 3.10
Classifier: Topic :: Software Development :: Libraries :: Python Modules
Classifier: Topic :: Utilities
License-File: LICENSE.rst
Requires-Dist: ctypes-window-info
